arcaflow_plugin_kill_pod.py
arcaflow_plugin_kill_pod-0.0.2.dist-info/LICENSE
arcaflow_plugin_kill_pod-0.0.2.dist-info/METADATA
arcaflow_plugin_kill_pod-0.0.2.dist-info/WHEEL
arcaflow_plugin_kill_pod-0.0.2.dist-info/RECORD
