Metadata-Version: 2.1
Name: arcaflow-plugin-kill-pod
Version: 0.0.2
Summary: Chaos Engineering Kill Pod Plugin for Arcaflow
Home-page: https://github.com/redhat-chaos/arcaflow-plugin-kill-pod
License: Apache-2.0
Requires-Python: >=3.9,<4.0
Classifier: Environment :: Plugins
Classifier: License :: OSI Approved :: Apache Software License
Classifier: Operating System :: OS Independent
Classifier: Programming Language :: Python :: 3
Classifier: Programming Language :: Python :: 3.9
Classifier: Programming Language :: Python :: 3.10
Classifier: Programming Language :: Python :: 3.11
Classifier: Programming Language :: Python :: 3
Requires-Dist: arcaflow-plugin-sdk (>=0.10.0,<0.11.0)
Requires-Dist: kubernetes (>=26.1.0,<27.0.0)
